xia_actor/__init__.py
xia_actor/actor.cpython-39-darwin.so
xia_actor/job.cpython-39-darwin.so
xia_actor/jobs/__init__.py
xia_actor/jobs/campaign_owner.cpython-39-darwin.so
xia_actor/jobs/mission_owner.cpython-39-darwin.so
xia_actor/jobs/mission_reviewer.cpython-39-darwin.so
xia_actor/jobs/mission_worker.cpython-39-darwin.so
xia_actor/jobs/target_reviewer.cpython-39-darwin.so
xia_actor/templates/prompts/coding.prompt
xia_actor/templates/prompts/error_locating.prompt
xia_actor/templates/prompts/fixing.prompt
xia_actor/templates/prompts/reviewing.prompt
xia_actor/templates/prompts/reworking.prompt
xia_actor/templates/prompts/test_coding.prompt
xia_actor/templates/prompts/working.prompt
xia_actor-0.1.7.dist-info/LICENSE.txt
xia_actor-0.1.7.dist-info/METADATA
xia_actor-0.1.7.dist-info/WHEEL
xia_actor-0.1.7.dist-info/top_level.txt
xia_actor-0.1.7.dist-info/RECORD
