Metadata-Version: 2.1
Name: xia-actor
Version: 0.1.7
Summary: UNKNOWN
Home-page: https://develop.x-i-a.com/docs/xia-actor/0.1.7/index.html
Author: X-I-A
Author-email: admin@x-i-a.com
License: UNKNOWN
Platform: UNKNOWN
Requires-Python: >=3.9
License-File: LICENSE.txt
Requires-Dist: jinja2
Requires-Dist: xia-engine
Requires-Dist: xia-composer
